lru2cache-0.1.2.dist-info/metadata.json
lru2cache-0.1.2.dist-info/DESCRIPTION.rst
lru2cache-0.1.2.dist-info/top_level.txt
lru2cache-0.1.2.dist-info/RECORD
lru2cache-0.1.2.dist-info/WHEEL
lru2cache-0.1.2.dist-info/METADATA
lru2cache/settings.py
lru2cache/wsgi.py
lru2cache/urls.py
lru2cache/__init__.py
lru2cache/utils.py
