Metadata-Version: 2.0
Name: lru2cache
Version: 0.1.2
Summary: A least recently used (LRU) 2 layer caching mechanism based in part on the Python 2.7 back-port of lru_cache
Home-page: https://github.com/pypa/sampleproject
Author: Michael J Brams
Author-email: mjbrams@3top.com
License: MIT
Keywords: cache caching memoize lru layered layer2 l1 l2 decorator fifo
Platform: UNKNOWN
Classifier: Development Status :: 3 - Alpha
Classifier: Operating System :: OS Independent
Classifier: Intended Audience :: Developers
Classifier: Topic :: Software Development :: Libraries :: Python Modules
Classifier: License :: OSI Approved :: MIT License
Classifier: Programming Language :: Python :: 2.7
Classifier: Programming Language :: Python :: 3.3
Classifier: Programming Language :: Python :: 3.4
Classifier: Framework :: Django :: 1.6
Classifier: Framework :: Django :: 1.7
Classifier: Framework :: Django :: 1.8
Provides-Extra: test
Requires-Dist: coverage; extra == 'test'
